my_math/__init__.py
my_math/unimore_math.py
unimore_lab_cicd_singh-0.4.dist-info/METADATA
unimore_lab_cicd_singh-0.4.dist-info/WHEEL
unimore_lab_cicd_singh-0.4.dist-info/top_level.txt
unimore_lab_cicd_singh-0.4.dist-info/RECORD
